<?xml version="1.0" encoding="UTF-8"?>
<objects serializationModel="Studio.01.10.00">
    <object class="AudioFile" id="{071cd45a-21cd-4167-a5f5-e8f1189b6da3}">
        <property name="assetPath">
            <value>creature_footStep_01.wav</value>
        </property>
        <property name="frequencyInKHz">
            <value>44.0999985</value>
        </property>
        <property name="channelCount">
            <value>2</value>
        </property>
        <property name="length">
            <value>2.6400000000000001</value>
        </property>
        <relationship name="masterAssetFolder">
            <destination>{d724fd05-6d07-4d08-819e-b21ddaa31cdf}</destination>
        </relationship>
    </object>
</objects>
